{
	"name": "level9",
	"layers": [
		{
			"name": "collisions",
			"overriden": 0,
			"instances": [
				{
					"type": "groundCollisions",
					"properties": {
						"initially-visible": true,
						"initial-animation": "Animation 1",
						"initial-frame": 0,
						"enable-collisions": true,
						"live-preview": false
					},
					"uid": 144,
					"instanceVariables": {},
					"behaviors": {
						"Physics": {
							"properties": {
								"immovable": true,
								"collision-mask": "use-collision-polygon",
								"prevent-rotation": false,
								"density": 1,
								"friction": 0.1,
								"elasticity": 0.5,
								"linear-damping": 0,
								"angular-damping": 0.01,
								"bullet": false,
								"enabled": true
							}
						}
					},
					"world": {
						"x": 241.3111988512576,
						"y": 448,
						"width": 472.6223977025152,
						"height": 63.102681759194006,
						"originX": 0.5,
						"originY": 0.5,
						"color": [
							1,
							1,
							1,
							1
						],
						"angle": 0,
						"zElevation": 0
					}
				},
				{
					"type": "groundCollisions",
					"properties": {
						"initially-visible": true,
						"initial-animation": "Animation 1",
						"initial-frame": 0,
						"enable-collisions": true,
						"live-preview": false
					},
					"uid": 145,
					"instanceVariables": {},
					"behaviors": {
						"Physics": {
							"properties": {
								"immovable": true,
								"collision-mask": "use-collision-polygon",
								"prevent-rotation": false,
								"density": 1,
								"friction": 0.1,
								"elasticity": 0.5,
								"linear-damping": 0,
								"angular-damping": 0.01,
								"bullet": false,
								"enabled": true
							}
						}
					},
					"world": {
						"x": 1330.9502772600458,
						"y": 449.12048809186246,
						"width": 351.74728369056027,
						"height": 63.102681759194006,
						"originX": 0.5,
						"originY": 0.5,
						"color": [
							1,
							1,
							1,
							1
						],
						"angle": 0,
						"zElevation": 0
					}
				},
				{
					"type": "hole",
					"properties": {
						"initially-visible": true,
						"initial-animation": "Animation 1",
						"initial-frame": 0,
						"enable-collisions": true,
						"live-preview": false
					},
					"uid": 146,
					"instanceVariables": {
						"nextLevelDelay": 1.5
					},
					"behaviors": {
						"Timer": {
							"properties": {}
						}
					},
					"world": {
						"x": 1529.8691822141666,
						"y": 476.0716044320808,
						"width": 66.802596,
						"height": 26.419215,
						"originX": 0.5,
						"originY": 0.5,
						"color": [
							1,
							1,
							1,
							1
						],
						"angle": 0,
						"zElevation": 0
					}
				},
				{
					"type": "waterCollisions4",
					"properties": {
						"initially-visible": true,
						"initial-animation": "Animation 1",
						"initial-frame": 0,
						"enable-collisions": true,
						"live-preview": false
					},
					"uid": 171,
					"instanceVariables": {},
					"behaviors": {},
					"world": {
						"x": 851.8999279887702,
						"y": 504.884819094573,
						"width": 897.9547152844068,
						"height": 46.149380521849594,
						"originX": 0.5,
						"originY": 0.5,
						"color": [
							1,
							1,
							1,
							1
						],
						"angle": 0,
						"zElevation": 0
					}
				},
				{
					"type": "groundCollisions",
					"properties": {
						"initially-visible": true,
						"initial-animation": "Animation 1",
						"initial-frame": 0,
						"enable-collisions": true,
						"live-preview": false
					},
					"uid": 147,
					"instanceVariables": {},
					"behaviors": {
						"Physics": {
							"properties": {
								"immovable": true,
								"collision-mask": "use-collision-polygon",
								"prevent-rotation": false,
								"density": 1,
								"friction": 0.1,
								"elasticity": 0.5,
								"linear-damping": 0,
								"angular-damping": 0.01,
								"bullet": false,
								"enabled": true
							}
						}
					},
					"world": {
						"x": 1640.0813240967007,
						"y": 448.64346711790466,
						"width": 170.77603855702944,
						"height": 63.102681759194006,
						"originX": 0.5,
						"originY": 0.5,
						"color": [
							1,
							1,
							1,
							1
						],
						"angle": 0,
						"zElevation": 0
					}
				},
				{
					"type": "wallCollisions2",
					"properties": {
						"initially-visible": true,
						"initial-animation": "Animation 1",
						"initial-frame": 0,
						"enable-collisions": true,
						"live-preview": false
					},
					"uid": 159,
					"instanceVariables": {},
					"behaviors": {
						"Physics": {
							"properties": {
								"immovable": true,
								"collision-mask": "use-collision-polygon",
								"prevent-rotation": false,
								"density": 1,
								"friction": 0,
								"elasticity": 0.1,
								"linear-damping": 0,
								"angular-damping": 0.01,
								"bullet": false,
								"enabled": true
							}
						}
					},
					"world": {
						"x": -25.8869388261636,
						"y": -510.8086093160692,
						"width": 52,
						"height": 1979.799651456165,
						"originX": 0.5,
						"originY": 0.5,
						"color": [
							1,
							1,
							1,
							1
						],
						"angle": 0,
						"zElevation": 0
					}
				},
				{
					"type": "wallCollisions2",
					"properties": {
						"initially-visible": true,
						"initial-animation": "Animation 1",
						"initial-frame": 0,
						"enable-collisions": true,
						"live-preview": false
					},
					"uid": 160,
					"instanceVariables": {},
					"behaviors": {
						"Physics": {
							"properties": {
								"immovable": true,
								"collision-mask": "use-collision-polygon",
								"prevent-rotation": false,
								"density": 1,
								"friction": 0,
								"elasticity": 0.1,
								"linear-damping": 0,
								"angular-damping": 0.01,
								"bullet": false,
								"enabled": true
							}
						}
					},
					"world": {
						"x": 1734.1383557589418,
						"y": -525.7232884821165,
						"width": 52,
						"height": 2010.799651456165,
						"originX": 0.5,
						"originY": 0.5,
						"color": [
							1,
							1,
							1,
							1
						],
						"angle": 0,
						"zElevation": 0
					}
				}
			],
			"sid": 394251948148990,
			"effectTypes": [],
			"isInitiallyVisible": true,
			"color": [
				1,
				1,
				1,
				1
			],
			"backgroundColor": [
				0.3686274509803922,
				0.3686274509803922,
				0.3686274509803922,
				1
			],
			"isTransparent": true,
			"parallaxX": 1,
			"parallaxY": 1,
			"scaleRate": 1,
			"forceOwnTexture": false,
			"renderingMode": "3d",
			"useRenderCells": false,
			"blendMode": "normal",
			"global": false
		},
		{
			"name": "bg7",
			"overriden": 0,
			"instances": [
				{
					"type": "forestBgL7",
					"properties": {
						"initially-visible": true,
						"origin": "top-left",
						"wrap-horizontal": "repeat",
						"wrap-vertical": "repeat",
						"image-offset-x": 0,
						"image-offset-y": 0,
						"image-scale-x": 1,
						"image-scale-y": 1,
						"image-angle": 0
					},
					"uid": 151,
					"instanceVariables": {},
					"behaviors": {},
					"world": {
						"x": 0,
						"y": 0,
						"width": 1708,
						"height": 480,
						"originX": 0,
						"originY": 0,
						"color": [
							1,
							1,
							1,
							1
						],
						"angle": 0,
						"zElevation": 0
					}
				}
			],
			"sid": 753271376238833,
			"effectTypes": [],
			"isInitiallyVisible": true,
			"color": [
				1,
				1,
				1,
				1
			],
			"backgroundColor": [
				0.3686274509803922,
				0.3686274509803922,
				0.3686274509803922,
				1
			],
			"isTransparent": true,
			"parallaxX": 1,
			"parallaxY": 1,
			"scaleRate": 1,
			"forceOwnTexture": false,
			"renderingMode": "3d",
			"useRenderCells": false,
			"blendMode": "normal",
			"global": false
		},
		{
			"name": "bg6",
			"overriden": 0,
			"instances": [
				{
					"type": "forestBgL6",
					"properties": {
						"initially-visible": true,
						"origin": "top-left",
						"wrap-horizontal": "repeat",
						"wrap-vertical": "repeat",
						"image-offset-x": 0,
						"image-offset-y": 0,
						"image-scale-x": 1,
						"image-scale-y": 1,
						"image-angle": 0
					},
					"uid": 152,
					"instanceVariables": {},
					"behaviors": {},
					"world": {
						"x": 0,
						"y": 0,
						"width": 1708,
						"height": 480,
						"originX": 0,
						"originY": 0,
						"color": [
							1,
							1,
							1,
							1
						],
						"angle": 0,
						"zElevation": 0
					}
				}
			],
			"sid": 235865211362214,
			"effectTypes": [],
			"isInitiallyVisible": true,
			"color": [
				1,
				1,
				1,
				1
			],
			"backgroundColor": [
				0.3686274509803922,
				0.3686274509803922,
				0.3686274509803922,
				1
			],
			"isTransparent": true,
			"parallaxX": 0.3,
			"parallaxY": 1,
			"scaleRate": 1,
			"forceOwnTexture": false,
			"renderingMode": "3d",
			"useRenderCells": false,
			"blendMode": "normal",
			"global": false
		},
		{
			"name": "bg5",
			"overriden": 0,
			"instances": [
				{
					"type": "forestBgL5",
					"properties": {
						"initially-visible": true,
						"origin": "top-left",
						"wrap-horizontal": "repeat",
						"wrap-vertical": "repeat",
						"image-offset-x": 0,
						"image-offset-y": 0,
						"image-scale-x": 1,
						"image-scale-y": 1,
						"image-angle": 0
					},
					"uid": 153,
					"instanceVariables": {},
					"behaviors": {},
					"world": {
						"x": 0,
						"y": 0,
						"width": 1708,
						"height": 480,
						"originX": 0,
						"originY": 0,
						"color": [
							1,
							1,
							1,
							1
						],
						"angle": 0,
						"zElevation": 0
					}
				}
			],
			"sid": 711477559266781,
			"effectTypes": [],
			"isInitiallyVisible": true,
			"color": [
				1,
				1,
				1,
				1
			],
			"backgroundColor": [
				0.3686274509803922,
				0.3686274509803922,
				0.3686274509803922,
				1
			],
			"isTransparent": true,
			"parallaxX": 0.45,
			"parallaxY": 1,
			"scaleRate": 1,
			"forceOwnTexture": false,
			"renderingMode": "3d",
			"useRenderCells": false,
			"blendMode": "normal",
			"global": false
		},
		{
			"name": "bg4",
			"overriden": 0,
			"instances": [
				{
					"type": "forestBgL4",
					"properties": {
						"initially-visible": true,
						"origin": "top-left",
						"wrap-horizontal": "repeat",
						"wrap-vertical": "repeat",
						"image-offset-x": 0,
						"image-offset-y": 0,
						"image-scale-x": 1,
						"image-scale-y": 1,
						"image-angle": 0
					},
					"uid": 154,
					"instanceVariables": {},
					"behaviors": {},
					"world": {
						"x": 0,
						"y": 0,
						"width": 1708,
						"height": 480,
						"originX": 0,
						"originY": 0,
						"color": [
							1,
							1,
							1,
							1
						],
						"angle": 0,
						"zElevation": 0
					}
				}
			],
			"sid": 621468367347117,
			"effectTypes": [],
			"isInitiallyVisible": true,
			"color": [
				1,
				1,
				1,
				1
			],
			"backgroundColor": [
				0.3686274509803922,
				0.3686274509803922,
				0.3686274509803922,
				1
			],
			"isTransparent": true,
			"parallaxX": 0.55,
			"parallaxY": 1,
			"scaleRate": 1,
			"forceOwnTexture": false,
			"renderingMode": "3d",
			"useRenderCells": false,
			"blendMode": "normal",
			"global": false
		},
		{
			"name": "bg3",
			"overriden": 0,
			"instances": [
				{
					"type": "forestBgL3",
					"properties": {
						"initially-visible": true,
						"origin": "top-left",
						"wrap-horizontal": "repeat",
						"wrap-vertical": "repeat",
						"image-offset-x": 0,
						"image-offset-y": 0,
						"image-scale-x": 1,
						"image-scale-y": 1,
						"image-angle": 0
					},
					"uid": 155,
					"instanceVariables": {},
					"behaviors": {},
					"world": {
						"x": 0,
						"y": 0,
						"width": 1708,
						"height": 480,
						"originX": 0,
						"originY": 0,
						"color": [
							1,
							1,
							1,
							1
						],
						"angle": 0,
						"zElevation": 0
					}
				}
			],
			"sid": 381417578055622,
			"effectTypes": [],
			"isInitiallyVisible": true,
			"color": [
				1,
				1,
				1,
				1
			],
			"backgroundColor": [
				0.3686274509803922,
				0.3686274509803922,
				0.3686274509803922,
				1
			],
			"isTransparent": true,
			"parallaxX": 0.6,
			"parallaxY": 1,
			"scaleRate": 1,
			"forceOwnTexture": false,
			"renderingMode": "3d",
			"useRenderCells": false,
			"blendMode": "normal",
			"global": false
		},
		{
			"name": "bg2",
			"overriden": 0,
			"instances": [
				{
					"type": "forestBgL2",
					"properties": {
						"initially-visible": true,
						"origin": "top-left",
						"wrap-horizontal": "repeat",
						"wrap-vertical": "repeat",
						"image-offset-x": 0,
						"image-offset-y": 0,
						"image-scale-x": 1,
						"image-scale-y": 1,
						"image-angle": 0
					},
					"uid": 156,
					"instanceVariables": {},
					"behaviors": {},
					"world": {
						"x": 0,
						"y": 0,
						"width": 1708,
						"height": 480,
						"originX": 0,
						"originY": 0,
						"color": [
							1,
							1,
							1,
							1
						],
						"angle": 0,
						"zElevation": 0
					}
				}
			],
			"sid": 821480610262328,
			"effectTypes": [],
			"isInitiallyVisible": true,
			"color": [
				1,
				1,
				1,
				1
			],
			"backgroundColor": [
				0.3686274509803922,
				0.3686274509803922,
				0.3686274509803922,
				1
			],
			"isTransparent": true,
			"parallaxX": 0.65,
			"parallaxY": 1,
			"scaleRate": 1,
			"forceOwnTexture": false,
			"renderingMode": "3d",
			"useRenderCells": false,
			"blendMode": "normal",
			"global": false
		},
		{
			"name": "bg",
			"overriden": 0,
			"instances": [
				{
					"type": "forestBgL1",
					"properties": {
						"initially-visible": true,
						"origin": "top-left",
						"wrap-horizontal": "repeat",
						"wrap-vertical": "repeat",
						"image-offset-x": 0,
						"image-offset-y": 0,
						"image-scale-x": 1,
						"image-scale-y": 1,
						"image-angle": 0
					},
					"uid": 157,
					"instanceVariables": {},
					"behaviors": {},
					"world": {
						"x": 0,
						"y": 0,
						"width": 1708,
						"height": 480,
						"originX": 0,
						"originY": 0,
						"color": [
							1,
							1,
							1,
							1
						],
						"angle": 0,
						"zElevation": 0
					}
				}
			],
			"sid": 970959800250794,
			"effectTypes": [],
			"isInitiallyVisible": true,
			"color": [
				1,
				1,
				1,
				1
			],
			"backgroundColor": [
				0.3686274509803922,
				0.3686274509803922,
				0.3686274509803922,
				1
			],
			"isTransparent": true,
			"parallaxX": 1,
			"parallaxY": 1,
			"scaleRate": 1,
			"forceOwnTexture": false,
			"renderingMode": "3d",
			"useRenderCells": false,
			"blendMode": "normal",
			"global": false
		},
		{
			"name": "ground",
			"overriden": 0,
			"instances": [
				{
					"type": "ceilingCollisions3",
					"properties": {
						"initially-visible": true,
						"initial-animation": "Animation 1",
						"initial-frame": 0,
						"enable-collisions": true,
						"live-preview": false
					},
					"uid": 161,
					"instanceVariables": {},
					"behaviors": {
						"Physics": {
							"properties": {
								"immovable": true,
								"collision-mask": "use-collision-polygon",
								"prevent-rotation": false,
								"density": 1,
								"friction": 1,
								"elasticity": 1.5,
								"linear-damping": 0,
								"angular-damping": 0.01,
								"bullet": false,
								"enabled": false
							}
						}
					},
					"world": {
						"x": 853.8457826842282,
						"y": -17.982045390101348,
						"width": 1708.4771272624162,
						"height": 36.835560675962256,
						"originX": 0.5,
						"originY": 0.5,
						"color": [
							1,
							1,
							1,
							1
						],
						"angle": 0,
						"zElevation": 0
					}
				},
				{
					"type": "water",
					"properties": {
						"initially-visible": true,
						"initial-animation": "Default",
						"initial-frame": 0,
						"enable-collisions": true,
						"live-preview": false
					},
					"uid": 170,
					"instanceVariables": {},
					"behaviors": {},
					"world": {
						"x": 819.3597081390711,
						"y": 443.0026742446508,
						"width": 805.562795083614,
						"height": 78.22557065495079,
						"originX": 0.5,
						"originY": 0.5,
						"color": [
							1,
							1,
							1,
							1
						],
						"angle": 0,
						"zElevation": 0
					}
				},
				{
					"type": "Tilemap",
					"properties": {
						"initially-visible": true,
						"tile-width": 32,
						"tile-height": 32,
						"tile-x-offset": 0,
						"tile-y-offset": 0,
						"tile-x-spacing": 0,
						"tile-y-spacing": 0,
						"tile-x-drawing-offset": 0,
						"tile-y-drawing-offset": 0,
						"drawing-mode": "top-to-right"
					},
					"uid": 158,
					"instanceVariables": {},
					"behaviors": {},
					"ownData": {
						"tilemapData": {
							"width": 54,
							"height": 15,
							"max-width": 95,
							"max-height": 52,
							"data": "13x0,5,11,50x0,5,11,50x0,5,11,50x0,5,11,50x0,5,11,50x0,5,11,50x0,5,11,50x0,5,11,50x0,5,11,50x0,5,11,50x0,5,11,50x0,5,11,50x0,5,11,50x0,5,11,49x0,28,13,20,44x0,5x28,3x29,44x0,8x29,44x0,8x29,44x0,5x29,4x28,43x0,8x29,44x0,8x29,44x0,8x29,44x0,8x29,44x0,8x29,44x0,8x29,44x0,8x29,44x0,8x29,44x0,8x29,44x0,8x29,44x0,2x29,4x28,46x0,6x29,2x28,44x0,6x29,2x28,44x0,6x29,2x28,46x0,4x29,2x28,46x0,4x29,2x28,46x0,4x29,2x28,46x0,4x29,7,14,46x0,4x29,5,11,46x0,4x29,5,11,46x0,4x29,5,11,46x0,4x29,5,11,50x0,5,11,50x0,5,11,50x0,5,11,50x0,5,11,50x0,5,11,50x0,5,11,50x0,5,11,50x0,5,11,50x0,5,11,50x0,5,11,50x0,5,11,50x0,5,11,50x0,5,11,51x0,11,2117x0"
						},
						"tile-width": 32,
						"tile-height": 32,
						"tile-x-offset": 0,
						"tile-y-offset": 0,
						"tile-x-spacing": 0,
						"tile-y-spacing": 0
					},
					"world": {
						"x": 0,
						"y": 0,
						"width": 1750,
						"height": 480,
						"originX": 0,
						"originY": 0,
						"color": [
							1,
							1,
							1,
							1
						],
						"zElevation": 0
					}
				}
			],
			"sid": 290623005447197,
			"effectTypes": [],
			"isInitiallyVisible": true,
			"color": [
				1,
				1,
				1,
				1
			],
			"backgroundColor": [
				0.3686274509803922,
				0.3686274509803922,
				0.3686274509803922,
				1
			],
			"isTransparent": true,
			"parallaxX": 1,
			"parallaxY": 1,
			"scaleRate": 1,
			"forceOwnTexture": false,
			"renderingMode": "3d",
			"useRenderCells": false,
			"blendMode": "normal",
			"global": false
		},
		{
			"name": "world",
			"overriden": 0,
			"instances": [
				{
					"type": "arrow",
					"properties": {
						"initially-visible": true,
						"initial-animation": "Default",
						"initial-frame": 0,
						"enable-collisions": true,
						"live-preview": false
					},
					"uid": 165,
					"instanceVariables": {},
					"behaviors": {},
					"world": {
						"x": 380,
						"y": 388,
						"width": 64,
						"height": 64,
						"originX": 0.5,
						"originY": 0.5,
						"color": [
							1,
							1,
							1,
							1
						],
						"angle": 0,
						"zElevation": 0
					}
				},
				{
					"type": "arrow",
					"properties": {
						"initially-visible": true,
						"initial-animation": "Animation 1",
						"initial-frame": 0,
						"enable-collisions": true,
						"live-preview": false
					},
					"uid": 172,
					"instanceVariables": {},
					"behaviors": {},
					"world": {
						"x": 320.65073802097334,
						"y": 388.3301476041946,
						"width": 64,
						"height": 64,
						"originX": 0.5,
						"originY": 0.5,
						"color": [
							1,
							1,
							1,
							1
						],
						"angle": 0,
						"zElevation": 0
					}
				},
				{
					"type": "Ball",
					"properties": {
						"initially-visible": true,
						"initial-animation": "Animation 1",
						"initial-frame": 0,
						"enable-collisions": true,
						"live-preview": false
					},
					"uid": 162,
					"instanceVariables": {
						"explosionDistance": 200,
						"explosionPower": 6,
						"maxExplodeSpeed": 5,
						"touchStarted": false,
						"noMovementTimeout": 0.6,
						"canHit": false,
						"state": "moving",
						"hitPower": 2,
						"onFloor": false,
						"hitPowerLengthMax": 300,
						"powerScale": 0,
						"hitPowerLength": 0
					},
					"behaviors": {
						"Physics": {
							"properties": {
								"immovable": false,
								"collision-mask": "circle",
								"prevent-rotation": true,
								"density": 1,
								"friction": 0.5,
								"elasticity": 0.5,
								"linear-damping": 0.7,
								"angular-damping": 18,
								"bullet": true,
								"enabled": true
							}
						},
						"ScrollTo": {
							"properties": {
								"enabled": true
							}
						},
						"Timer": {
							"properties": {}
						},
						"BallState": {
							"properties": {
								"active": true,
								"start-state": "moving"
							}
						}
					},
					"world": {
						"x": 175.38051515117732,
						"y": 340.1406403273271,
						"width": 30,
						"height": 30,
						"originX": 0.6009389671361502,
						"originY": 0.6009389671361502,
						"color": [
							1,
							1,
							1,
							1
						],
						"angle": 0,
						"zElevation": 0
					}
				},
				{
					"type": "Flag",
					"properties": {
						"initially-visible": true,
						"initial-animation": "Default",
						"initial-frame": 2,
						"enable-collisions": true,
						"live-preview": false
					},
					"uid": 163,
					"instanceVariables": {},
					"behaviors": {},
					"world": {
						"x": 1548.8691822141666,
						"y": 359.0716044320808,
						"width": 64,
						"height": 128,
						"originX": 0.5,
						"originY": 0.5,
						"color": [
							1,
							1,
							1,
							1
						],
						"angle": 0,
						"zElevation": 0
					}
				},
				{
					"type": "goal",
					"properties": {
						"initially-visible": true,
						"initial-animation": "Default",
						"initial-frame": 0,
						"enable-collisions": true,
						"live-preview": false
					},
					"uid": 164,
					"instanceVariables": {},
					"behaviors": {},
					"world": {
						"x": 1529.8691822141666,
						"y": 447.0716044320808,
						"width": 70,
						"height": 70,
						"originX": 0.5,
						"originY": 0.5,
						"color": [
							1,
							1,
							1,
							1
						],
						"angle": 0,
						"zElevation": 0
					}
				}
			],
			"sid": 380557130417095,
			"effectTypes": [],
			"isInitiallyVisible": true,
			"color": [
				1,
				1,
				1,
				1
			],
			"backgroundColor": [
				0.3686274509803922,
				0.3686274509803922,
				0.3686274509803922,
				1
			],
			"isTransparent": true,
			"parallaxX": 1,
			"parallaxY": 1,
			"scaleRate": 1,
			"forceOwnTexture": false,
			"renderingMode": "3d",
			"useRenderCells": false,
			"blendMode": "normal",
			"global": false
		},
		{
			"name": "HUD",
			"overriden": 1,
			"instances": [
				{
					"type": "explodeButton",
					"properties": {
						"initially-visible": true,
						"initial-animation": "normal",
						"initial-frame": 0,
						"enable-collisions": true,
						"live-preview": false
					},
					"uid": 166,
					"instanceVariables": {},
					"behaviors": {
						"Anchor": {
							"properties": {
								"left-edge": "window-left",
								"top-edge": "window-top",
								"right-edge": "none",
								"bottom-edge": "none",
								"enabled": true
							}
						},
						"Flash": {
							"properties": {}
						}
					},
					"world": {
						"x": 320,
						"y": 64,
						"width": 180,
						"height": 81,
						"originX": 0.5,
						"originY": 0.5,
						"color": [
							1,
							1,
							1,
							1
						],
						"angle": 0,
						"zElevation": 0
					}
				},
				{
					"type": "exploddeText",
					"properties": {
						"text": "Explode",
						"enable-bbcode": true,
						"font": "LuckiestGuy-Regular",
						"size": 18,
						"line-height": 0,
						"bold": false,
						"italic": false,
						"color": [
							1,
							1,
							1,
							1
						],
						"horizontal-alignment": "center",
						"vertical-alignment": "top",
						"wrapping": "word",
						"initially-visible": true,
						"origin": "center"
					},
					"uid": 167,
					"instanceVariables": {},
					"behaviors": {
						"Anchor": {
							"properties": {
								"left-edge": "window-left",
								"top-edge": "window-top",
								"right-edge": "none",
								"bottom-edge": "none",
								"enabled": true
							}
						},
						"Flash": {
							"properties": {}
						}
					},
					"world": {
						"x": 288,
						"y": 208,
						"width": 112,
						"height": 32,
						"originX": 0.5,
						"originY": 0.5,
						"color": [
							1,
							1,
							1,
							1
						],
						"angle": 0,
						"zElevation": 0
					}
				},
				{
					"type": "explosion",
					"properties": {
						"initially-visible": true,
						"initial-animation": "explode",
						"initial-frame": 0,
						"enable-collisions": true,
						"live-preview": false
					},
					"uid": 168,
					"instanceVariables": {},
					"behaviors": {
						"Fade": {
							"properties": {
								"fade-in-time": 0,
								"wait-time": 0.25,
								"fade-out-time": 0.25,
								"destroy": true,
								"enabled": true,
								"live-preview": false
							}
						}
					},
					"world": {
						"x": 208,
						"y": 672,
						"width": 167,
						"height": 165,
						"originX": 0.4251497005988024,
						"originY": 0.4636363636363636,
						"color": [
							1,
							1,
							1,
							1
						],
						"angle": 0,
						"zElevation": 0
					}
				},
				{
					"type": "Start",
					"properties": {
						"initially-visible": false,
						"initial-animation": "Animation 1",
						"initial-frame": 0,
						"enable-collisions": true,
						"live-preview": false
					},
					"uid": 169,
					"instanceVariables": {},
					"behaviors": {},
					"world": {
						"x": 103,
						"y": 304,
						"width": 95,
						"height": 97,
						"originX": 0.5,
						"originY": 0.5,
						"color": [
							1,
							1,
							1,
							1
						],
						"angle": 0,
						"zElevation": 0
					}
				}
			],
			"sid": 911505121865700,
			"effectTypes": [],
			"isInitiallyVisible": true,
			"color": [
				1,
				1,
				1,
				1
			],
			"backgroundColor": [
				0.3686274509803922,
				0.3686274509803922,
				0.3686274509803922,
				1
			],
			"isTransparent": true,
			"parallaxX": 1,
			"parallaxY": 1,
			"scaleRate": 1,
			"forceOwnTexture": false,
			"renderingMode": "3d",
			"useRenderCells": false,
			"blendMode": "normal",
			"global": false
		}
	],
	"sid": 708556680469504,
	"nonworld-instances": [],
	"effectTypes": [],
	"width": 1708,
	"height": 480,
	"unboundedScrolling": false,
	"eventSheet": "MainCode"
}