{
	"name": "level5",
	"layers": [
		{
			"name": "collisions",
			"overriden": 0,
			"instances": [
				{
					"type": "groundCollisions",
					"properties": {
						"initially-visible": true,
						"initial-animation": "Animation 1",
						"initial-frame": 0,
						"enable-collisions": true,
						"live-preview": false
					},
					"uid": 56,
					"instanceVariables": {},
					"behaviors": {
						"Physics": {
							"properties": {
								"immovable": true,
								"collision-mask": "use-collision-polygon",
								"prevent-rotation": false,
								"density": 1,
								"friction": 0.1,
								"elasticity": 0.5,
								"linear-damping": 0,
								"angular-damping": 0.01,
								"bullet": false,
								"enabled": true
							}
						}
					},
					"world": {
						"x": 374.9000751314801,
						"y": 448,
						"width": 739.8001502629602,
						"height": 63.102681759194006,
						"originX": 0.5,
						"originY": 0.5,
						"color": [
							1,
							1,
							1,
							1
						],
						"angle": 0,
						"zElevation": 0
					}
				},
				{
					"type": "groundCollisions",
					"properties": {
						"initially-visible": true,
						"initial-animation": "Animation 1",
						"initial-frame": 0,
						"enable-collisions": true,
						"live-preview": false
					},
					"uid": 83,
					"instanceVariables": {},
					"behaviors": {
						"Physics": {
							"properties": {
								"immovable": true,
								"collision-mask": "use-collision-polygon",
								"prevent-rotation": false,
								"density": 1,
								"friction": 0.1,
								"elasticity": 0.5,
								"linear-damping": 0,
								"angular-damping": 0.01,
								"bullet": false,
								"enabled": true
							}
						}
					},
					"world": {
						"x": 862.1561573539733,
						"y": 447.8494974447436,
						"width": 140.8949494623398,
						"height": 63.102681759194006,
						"originX": 0.5,
						"originY": 0.5,
						"color": [
							1,
							1,
							1,
							1
						],
						"angle": 0,
						"zElevation": 0
					}
				},
				{
					"type": "hole",
					"properties": {
						"initially-visible": true,
						"initial-animation": "Animation 1",
						"initial-frame": 0,
						"enable-collisions": true,
						"live-preview": false
					},
					"uid": 84,
					"instanceVariables": {
						"nextLevelDelay": 1.5
					},
					"behaviors": {
						"Timer": {
							"properties": {}
						}
					},
					"world": {
						"x": 767.038549,
						"y": 478.578957,
						"width": 66.802596,
						"height": 26.419215,
						"originX": 0.5,
						"originY": 0.5,
						"color": [
							1,
							1,
							1,
							1
						],
						"angle": 0,
						"zElevation": 0
					}
				}
			],
			"sid": 514911376595464,
			"effectTypes": [],
			"isInitiallyVisible": true,
			"color": [
				1,
				1,
				1,
				1
			],
			"backgroundColor": [
				0.3686274509803922,
				0.3686274509803922,
				0.3686274509803922,
				1
			],
			"isTransparent": true,
			"parallaxX": 1,
			"parallaxY": 1,
			"scaleRate": 1,
			"forceOwnTexture": false,
			"renderingMode": "3d",
			"useRenderCells": false,
			"blendMode": "normal",
			"global": false
		},
		{
			"name": "bg",
			"overriden": 0,
			"instances": [
				{
					"type": "forestBg",
					"properties": {
						"initially-visible": true,
						"origin": "top-left",
						"wrap-horizontal": "repeat",
						"wrap-vertical": "repeat",
						"image-offset-x": 0,
						"image-offset-y": 0,
						"image-scale-x": 1,
						"image-scale-y": 1,
						"image-angle": 0
					},
					"uid": 58,
					"instanceVariables": {},
					"behaviors": {
						"Anchor": {
							"properties": {
								"left-edge": "window-left",
								"top-edge": "window-top",
								"right-edge": "none",
								"bottom-edge": "none",
								"enabled": true
							}
						}
					},
					"world": {
						"x": 0,
						"y": 0,
						"width": 854,
						"height": 480,
						"originX": 0,
						"originY": 0,
						"color": [
							1,
							1,
							1,
							1
						],
						"angle": 0,
						"zElevation": 0
					}
				}
			],
			"sid": 133347746777964,
			"effectTypes": [],
			"isInitiallyVisible": true,
			"color": [
				1,
				1,
				1,
				1
			],
			"backgroundColor": [
				0.3686274509803922,
				0.3686274509803922,
				0.3686274509803922,
				1
			],
			"isTransparent": false,
			"parallaxX": 1,
			"parallaxY": 1,
			"scaleRate": 1,
			"forceOwnTexture": false,
			"renderingMode": "3d",
			"useRenderCells": false,
			"blendMode": "normal",
			"global": false
		},
		{
			"name": "ground",
			"overriden": 0,
			"instances": [
				{
					"type": "Tilemap",
					"properties": {
						"initially-visible": true,
						"tile-width": 32,
						"tile-height": 32,
						"tile-x-offset": 0,
						"tile-y-offset": 0,
						"tile-x-spacing": 0,
						"tile-y-spacing": 0,
						"tile-x-drawing-offset": 0,
						"tile-y-drawing-offset": 0,
						"drawing-mode": "top-to-right"
					},
					"uid": 59,
					"instanceVariables": {},
					"behaviors": {},
					"ownData": {
						"tilemapData": {
							"width": 27,
							"height": 15,
							"max-width": 68,
							"max-height": 52,
							"data": "13x0,5,11,50x0,5,11,50x0,5,11,50x0,5,11,50x0,5,11,50x0,5,11,50x0,5,11,50x0,5,11,50x0,5,11,50x0,5,11,50x0,5,11,50x0,5,11,50x0,5,11,50x0,5,11,50x0,5,11,50x0,5,11,50x0,5,11,50x0,5,11,50x0,5,11,50x0,5,11,50x0,5,11,50x0,5,11,50x0,5,11,50x0,5,11,50x0,5,11,50x0,5,11,50x0,5,11,2169x0"
						},
						"tile-width": 32,
						"tile-height": 32,
						"tile-x-offset": 0,
						"tile-y-offset": 0,
						"tile-x-spacing": 0,
						"tile-y-spacing": 0
					},
					"world": {
						"x": 0,
						"y": 0,
						"width": 875,
						"height": 480,
						"originX": 0,
						"originY": 0,
						"color": [
							1,
							1,
							1,
							1
						],
						"zElevation": 0
					}
				}
			],
			"sid": 270547342825754,
			"effectTypes": [],
			"isInitiallyVisible": true,
			"color": [
				1,
				1,
				1,
				1
			],
			"backgroundColor": [
				0.3686274509803922,
				0.3686274509803922,
				0.3686274509803922,
				1
			],
			"isTransparent": true,
			"parallaxX": 1,
			"parallaxY": 1,
			"scaleRate": 1,
			"forceOwnTexture": false,
			"renderingMode": "3d",
			"useRenderCells": false,
			"blendMode": "normal",
			"global": false
		},
		{
			"name": "world",
			"overriden": 0,
			"instances": [
				{
					"type": "Ball",
					"properties": {
						"initially-visible": true,
						"initial-animation": "Animation 1",
						"initial-frame": 0,
						"enable-collisions": true,
						"live-preview": false
					},
					"uid": 61,
					"instanceVariables": {
						"explosionDistance": 200,
						"explosionPower": 6,
						"maxExplodeSpeed": 5,
						"touchStarted": false,
						"noMovementTimeout": 0.6,
						"canHit": false,
						"state": "moving",
						"hitPower": 2,
						"onFloor": false,
						"hitPowerLengthMax": 300,
						"powerScale": 0,
						"hitPowerLength": 0
					},
					"behaviors": {
						"Physics": {
							"properties": {
								"immovable": false,
								"collision-mask": "circle",
								"prevent-rotation": true,
								"density": 1,
								"friction": 0.5,
								"elasticity": 0.5,
								"linear-damping": 0.7,
								"angular-damping": 18,
								"bullet": true,
								"enabled": true
							}
						},
						"ScrollTo": {
							"properties": {
								"enabled": true
							}
						},
						"Timer": {
							"properties": {}
						},
						"BallState": {
							"properties": {
								"active": true,
								"start-state": "moving"
							}
						}
					},
					"world": {
						"x": 175.38051515117732,
						"y": 340.1406403273271,
						"width": 30,
						"height": 30,
						"originX": 0.6009389671361502,
						"originY": 0.6009389671361502,
						"color": [
							1,
							1,
							1,
							1
						],
						"angle": 0,
						"zElevation": 0
					}
				},
				{
					"type": "Flag",
					"properties": {
						"initially-visible": true,
						"initial-animation": "Default",
						"initial-frame": 2,
						"enable-collisions": true,
						"live-preview": false
					},
					"uid": 60,
					"instanceVariables": {},
					"behaviors": {},
					"world": {
						"x": 786.6911259743614,
						"y": 358.4398280486946,
						"width": 64,
						"height": 128,
						"originX": 0.5,
						"originY": 0.5,
						"color": [
							1,
							1,
							1,
							1
						],
						"angle": 0,
						"zElevation": 0
					}
				},
				{
					"type": "glassBlock",
					"properties": {
						"initially-visible": true,
						"initial-animation": "normal",
						"initial-frame": 0,
						"enable-collisions": true,
						"live-preview": false
					},
					"uid": 63,
					"instanceVariables": {
						"health": 3
					},
					"behaviors": {
						"Physics2": {
							"properties": {
								"immovable": true,
								"collision-mask": "use-collision-polygon",
								"prevent-rotation": false,
								"density": 1,
								"friction": 0.5,
								"elasticity": 0.7,
								"linear-damping": 0,
								"angular-damping": 0.01,
								"bullet": false,
								"enabled": true
							}
						},
						"DestroyOutsideLayout": {
							"properties": {}
						}
					},
					"world": {
						"x": 1632,
						"y": 112,
						"width": 32,
						"height": 32,
						"originX": 0.5,
						"originY": 0.5,
						"color": [
							1,
							1,
							1,
							1
						],
						"angle": 0,
						"zElevation": 0
					}
				},
				{
					"type": "glassBlock",
					"properties": {
						"initially-visible": true,
						"initial-animation": "normal",
						"initial-frame": 0,
						"enable-collisions": true,
						"live-preview": false
					},
					"uid": 66,
					"instanceVariables": {
						"health": 3
					},
					"behaviors": {
						"Physics2": {
							"properties": {
								"immovable": true,
								"collision-mask": "use-collision-polygon",
								"prevent-rotation": false,
								"density": 1,
								"friction": 0.5,
								"elasticity": 0.7,
								"linear-damping": 0,
								"angular-damping": 0.01,
								"bullet": false,
								"enabled": true
							}
						},
						"DestroyOutsideLayout": {
							"properties": {}
						}
					},
					"world": {
						"x": 1632,
						"y": 48,
						"width": 32,
						"height": 32,
						"originX": 0.5,
						"originY": 0.5,
						"color": [
							1,
							1,
							1,
							1
						],
						"angle": 0,
						"zElevation": 0
					}
				},
				{
					"type": "glassBlock",
					"properties": {
						"initially-visible": true,
						"initial-animation": "normal",
						"initial-frame": 0,
						"enable-collisions": true,
						"live-preview": false
					},
					"uid": 57,
					"instanceVariables": {
						"health": 3
					},
					"behaviors": {
						"Physics2": {
							"properties": {
								"immovable": true,
								"collision-mask": "use-collision-polygon",
								"prevent-rotation": false,
								"density": 1,
								"friction": 0.5,
								"elasticity": 0.7,
								"linear-damping": 0,
								"angular-damping": 0.01,
								"bullet": false,
								"enabled": true
							}
						},
						"DestroyOutsideLayout": {
							"properties": {}
						}
					},
					"world": {
						"x": 1632,
						"y": 144,
						"width": 32,
						"height": 32,
						"originX": 0.5,
						"originY": 0.5,
						"color": [
							1,
							1,
							1,
							1
						],
						"angle": 0,
						"zElevation": 0
					}
				},
				{
					"type": "goal",
					"properties": {
						"initially-visible": true,
						"initial-animation": "Default",
						"initial-frame": 0,
						"enable-collisions": true,
						"live-preview": false
					},
					"uid": 82,
					"instanceVariables": {},
					"behaviors": {},
					"world": {
						"x": 768.9104043255295,
						"y": 448.72829623366914,
						"width": 70,
						"height": 70,
						"originX": 0.5,
						"originY": 0.5,
						"color": [
							1,
							1,
							1,
							1
						],
						"angle": 0,
						"zElevation": 0
					}
				}
			],
			"sid": 194113820466407,
			"effectTypes": [],
			"isInitiallyVisible": true,
			"color": [
				1,
				1,
				1,
				1
			],
			"backgroundColor": [
				0.3686274509803922,
				0.3686274509803922,
				0.3686274509803922,
				1
			],
			"isTransparent": true,
			"parallaxX": 1,
			"parallaxY": 1,
			"scaleRate": 1,
			"forceOwnTexture": false,
			"renderingMode": "3d",
			"useRenderCells": false,
			"blendMode": "normal",
			"global": false
		},
		{
			"name": "HUD",
			"overriden": 1,
			"instances": [
				{
					"type": "explodeButton",
					"properties": {
						"initially-visible": true,
						"initial-animation": "normal",
						"initial-frame": 0,
						"enable-collisions": true,
						"live-preview": false
					},
					"uid": 79,
					"instanceVariables": {},
					"behaviors": {
						"Anchor": {
							"properties": {
								"left-edge": "window-left",
								"top-edge": "window-top",
								"right-edge": "none",
								"bottom-edge": "none",
								"enabled": true
							}
						}
					},
					"world": {
						"x": 320,
						"y": 64,
						"width": 180,
						"height": 81,
						"originX": 0.5,
						"originY": 0.5,
						"color": [
							1,
							1,
							1,
							1
						],
						"angle": 0,
						"zElevation": 0
					}
				},
				{
					"type": "exploddeText",
					"properties": {
						"text": "Explode",
						"enable-bbcode": true,
						"font": "LuckiestGuy-Regular",
						"size": 18,
						"line-height": 0,
						"bold": false,
						"italic": false,
						"color": [
							1,
							1,
							1,
							1
						],
						"horizontal-alignment": "center",
						"vertical-alignment": "top",
						"wrapping": "word",
						"initially-visible": true,
						"origin": "center"
					},
					"uid": 77,
					"instanceVariables": {},
					"behaviors": {
						"Anchor": {
							"properties": {
								"left-edge": "window-left",
								"top-edge": "window-top",
								"right-edge": "none",
								"bottom-edge": "none",
								"enabled": true
							}
						}
					},
					"world": {
						"x": 288,
						"y": 208,
						"width": 112,
						"height": 32,
						"originX": 0.5,
						"originY": 0.5,
						"color": [
							1,
							1,
							1,
							1
						],
						"angle": 0,
						"zElevation": 0
					}
				},
				{
					"type": "explosion",
					"properties": {
						"initially-visible": true,
						"initial-animation": "explode",
						"initial-frame": 0,
						"enable-collisions": true,
						"live-preview": false
					},
					"uid": 80,
					"instanceVariables": {},
					"behaviors": {
						"Fade": {
							"properties": {
								"fade-in-time": 0,
								"wait-time": 0.25,
								"fade-out-time": 0.25,
								"destroy": true,
								"enabled": true,
								"live-preview": false
							}
						}
					},
					"world": {
						"x": 208,
						"y": 672,
						"width": 167,
						"height": 165,
						"originX": 0.4251497005988024,
						"originY": 0.4636363636363636,
						"color": [
							1,
							1,
							1,
							1
						],
						"angle": 0,
						"zElevation": 0
					}
				},
				{
					"type": "Start",
					"properties": {
						"initially-visible": false,
						"initial-animation": "Animation 1",
						"initial-frame": 0,
						"enable-collisions": true,
						"live-preview": false
					},
					"uid": 81,
					"instanceVariables": {},
					"behaviors": {},
					"world": {
						"x": 103,
						"y": 304,
						"width": 95,
						"height": 97,
						"originX": 0.5,
						"originY": 0.5,
						"color": [
							1,
							1,
							1,
							1
						],
						"angle": 0,
						"zElevation": 0
					}
				}
			],
			"sid": 997265351422869,
			"effectTypes": [],
			"isInitiallyVisible": true,
			"color": [
				1,
				1,
				1,
				1
			],
			"backgroundColor": [
				0.3686274509803922,
				0.3686274509803922,
				0.3686274509803922,
				1
			],
			"isTransparent": true,
			"parallaxX": 1,
			"parallaxY": 1,
			"scaleRate": 1,
			"forceOwnTexture": false,
			"renderingMode": "3d",
			"useRenderCells": false,
			"blendMode": "normal",
			"global": false
		}
	],
	"sid": 445372668480230,
	"nonworld-instances": [],
	"effectTypes": [],
	"width": 854,
	"height": 480,
	"unboundedScrolling": false,
	"eventSheet": "MainCode"
}